buildgrid/common/__init__.py
buildgrid/common/config.py
buildgrid/common/py.typed
buildgrid/common/auth/__init__.py
buildgrid/common/auth/config.py
buildgrid/common/auth/enums.py
buildgrid/common/auth/exceptions.py
buildgrid/common/auth/manager.py
buildgrid/common/metrics/__init__.py
buildgrid/common/metrics/log_metric_publisher.py
buildgrid/common/metrics/metric_publisher.py
buildgrid/common/metrics/statsd_metric_publisher.py
buildgrid/common/protos/__init__.py
buildgrid/common/protos/build/bazel/remote/asset/v1/__init__.py
buildgrid/common/protos/build/bazel/remote/asset/v1/remote_asset_pb2.py
buildgrid/common/protos/build/bazel/remote/asset/v1/remote_asset_pb2.pyi
buildgrid/common/protos/build/bazel/remote/asset/v1/remote_asset_pb2_grpc.py
buildgrid/common/protos/build/bazel/remote/asset/v1/remote_asset_pb2_grpc.pyi
buildgrid/common/protos/build/bazel/remote/asset/v1/remote_asset_pb2_grpc_aio.py
buildgrid/common/protos/build/bazel/remote/asset/v1/remote_asset_pb2_grpc_aio.pyi
buildgrid/common/protos/build/bazel/remote/execution/v2/__init__.py
buildgrid/common/protos/build/bazel/remote/execution/v2/remote_execution_pb2.py
buildgrid/common/protos/build/bazel/remote/execution/v2/remote_execution_pb2.pyi
buildgrid/common/protos/build/bazel/remote/execution/v2/remote_execution_pb2_grpc.py
buildgrid/common/protos/build/bazel/remote/execution/v2/remote_execution_pb2_grpc.pyi
buildgrid/common/protos/build/bazel/remote/execution/v2/remote_execution_pb2_grpc_aio.py
buildgrid/common/protos/build/bazel/remote/execution/v2/remote_execution_pb2_grpc_aio.pyi
buildgrid/common/protos/build/bazel/remote/logstream/v1/__init__.py
buildgrid/common/protos/build/bazel/remote/logstream/v1/remote_logstream_pb2.py
buildgrid/common/protos/build/bazel/remote/logstream/v1/remote_logstream_pb2.pyi
buildgrid/common/protos/build/bazel/remote/logstream/v1/remote_logstream_pb2_grpc.py
buildgrid/common/protos/build/bazel/remote/logstream/v1/remote_logstream_pb2_grpc.pyi
buildgrid_common-0.5.2.dist-info/licenses/LICENSE
buildgrid_common-0.5.2.dist-info/METADATA
buildgrid_common-0.5.2.dist-info/WHEEL
buildgrid_common-0.5.2.dist-info/top_level.txt
buildgrid_common-0.5.2.dist-info/RECORD
